Metadata-Version: 1.1
Name: sqlbuilder
Version: 0.7.10.18
Summary: SmartSQL - lightweight sql builder.
Home-page: https://bitbucket.org/emacsway/sqlbuilder
Author: Ivan Zakrevsky and contributors
Author-email: ivzak@yandex.ru
License: BSD License
Keywords: SQL database
Platform: UNKNOWN
Classifier: Development Status :: 5 - Production/Stable
Classifier: Intended Audience :: Developers
Classifier: License :: OSI Approved :: BSD License
Classifier: Operating System :: OS Independent
Classifier: Programming Language :: Python
Classifier: Programming Language :: Python :: 2
Classifier: Programming Language :: Python :: 2.7
Classifier: Programming Language :: Python :: 3
Classifier: Programming Language :: Python :: 3.2
Classifier: Programming Language :: Python :: 3.3
Classifier: Programming Language :: Python :: 3.4
Classifier: Topic :: Software Development :: Libraries :: Python Modules
